{
  "amo": {
    "principal_parts": ["amo", "amare", "amavi", "amatum"],
    "conjugation": "first",
    "eng": "to love, like",
    "idioms": {
      "amabo te": "please"
    }
  },
  "cogito": {
    "principal_parts": ["cogito", "cogitare", "cogitavi", "cogitatum"],
    "conjugation": "first",
    "eng": "to think, ponder, consider, plan"
  },
  "debeo": {
    "principal_parts": ["debeo", "debere", "debui", "debitum"],
    "conjugation": "second",
    "eng": "to owe; ought, must, should"
  },
  "do": {
    "principal_parts": ["do", "dare", "dedi", "datum"],
    "conjugation": "first",
    "eng": "to give, offer"
  },
  "erro": {
    "principal_parts": ["erro", "errare", "erravi", "erratum"],
    "conjugation": "first",
    "eng": "to wander; err, go astray, make a mistake, be mistaken"
  },
  "laudo": {
    "principal_parts": ["laudo", "laudare", "laudavi", "laudatum"],
    "conjugation": "first",
    "eng": "to praise"
  },
  "moneo": {
    "principal_parts": ["moneo", "monere", "monui", "monitum"],
    "conjugation": "second",
    "eng": "to remind, advise, warn"
  },
  "salveo": {
    "principal_parts": ["salveo", "salvere"],
    "conjugation": "second",
    "eng": "to be well, be in good health"
  },
  "salve": {
    "principal_parts": ["salve", "salvete"],
    "conjugation": "second",
    "eng": "hello, greetings!"
  },
  "servo": {
    "principal_parts": ["servo", "servare", "servavi", "servatum"],
    "conjugation": "first",
    "eng": "to preserve, save, keep, guard"
  },
  "conservo": {
    "principal_parts": ["conservo", "conservare", "conservavi", "conservatum"],
    "conjugation": "first",
    "eng": "a stronger form of servo, to preserve, conserve, maintain"
  },
  "terreo": {
    "principal_parts": ["terreo", "terrere", "terrui", "territum"],
    "conjugation": "second",
    "eng": "to frighten, terrify"
  },
  "valeo": {
    "principal_parts": ["valeo", "valere", "valui", "valiturum"],
    "conjugation": "second",
    "eng": "to be strong, have power; be well"
  },
  "video": {
    "principal_parts": ["video", "videre", "vidi", "visum"],
    "conjugation": "second",
    "eng": "to see; observe, understand"
  },
  "voco": {
    "principal_parts": ["voco", "vocare", "vocavi", "vocatum"],
    "conjugation": "first",
    "eng": "to call, summon"
  },
  "habeo": {
    "principal_parts": ["habeo", "habere", "habui", "habitum"],
    "conjugation": "second",
    "eng": "to have, hold, possess; consider, regard"
  },
  "satio": {
    "principal_parts": ["satio", "satiare", "satiavi", "satiatum"],
    "conjugation": "first",
    "eng": "to satisfy, sate"
  },
  "iuvo": {
    "principal_parts": ["iuvo", "iuvare", "iuvi", "iutum"],
    "conjugation": "first",
    "eng": "to help, aid, assist; please"
  },
  "adiuvo": {
    "principal_parts": ["adiuvo", "adiuvare", "adiuvi", "adiutum"],
    "conjugation": "first",
    "eng": "to help, aid, assist; please"
  },
  "sum": {
    "principal_parts": ["sum", "esse", "fui", "futurum"],
    "conjugation": "irregular",
    "eng": "to be, exist"
  },
  "ceno": {
    "principal_parts": ["ceno", "cenare", "cenavi", "cenatum"],
    "conjugation": "first",
    "eng": "to dine"
  },
  "culpo": {
    "principal_parts": ["culpo", "culpare", "culpavi", "culpatum"],
    "conjugation": "first",
    "eng": "to blame, censure"
  },
  "maneo": {
    "principal_parts": ["maneo", "manere", "mansi", "mansum"],
    "conjugation": "second",
    "eng": "to remain, stay, stay behind, abide, continue"
  },
  "remaneo": {
    "principal_parts": ["remaneo", "remanere", "remansi", "remansum"],
    "conjugation": "second",
    "eng": "to remain, stay, stay behind, abide, continue"
  },
  "supero": {
    "principal_parts": ["supero", "superare", "superavi", "superatum"],
    "conjugation": "first",
    "eng": "to be above, have the upper hand, surpass; overcome, conquer"
  },
  "possum": {
    "principal_parts": ["possum", "posse", "potui"],
    "conjugation": "irregular",
    "eng": "to be able, can, could, have power"
  },
  "tolero": {
    "principal_parts": ["tolero", "tolerare", "toleravi", "toleratum"],
    "conjugation": "first",
    "eng": "to bear, endure"
  }
}